{ 
    "shared": [
    {
        "Number": "",
        "machineNumber": "",
        "Component": "",
        "CleaningTools": "",
        "Operation": "",
        "MachineStatus": "",
        "Exp. Time (min)": "",
        "When": "",
        "OPL": ""
    },
    {
        "Number": "1",
        "machineNumber": "Roll Dr.",
        "Component": "Production Line",
        "CleaningTools": "Visual Inspection",
        "Operation": "Did you receive your production line in an adequate state of cleanliness and condition indicating the previous shift performed effective cleaning or inspection to prevent contamination?  If not, notify your crew leader and take corrective action.",
        "MachineStatus": "Up/Down",
        "Exp. Time (min)": "",
        "When": "SOS",
        "OPL": ""
    },
    {
        "Number": "2",
        "machineNumber": "Roll Dr.",
        "Component": "Powered Industrial Hand Truck",
        "CleaningTools": "Visual Inspection of Items on FM SF 029",
        "Operation": "Powered Industrial Hand Truck Pre-Use Inspection must be completed prior to operating on each shift. If any items need attention NO NOT operate. Notify your crew leader and enter a work order for repair.",
        "MachineStatus": "Up/Down",
        "Exp. Time (min)": "",
        "When": "SOS",
        "OPL": "FM-SF-029"
    },
    {
        "Number": "3",
        "machineNumber": "Roll Dr.",
        "Component": "Hoist",
        "CleaningTools": "Visual Inspection of Items on FM CO 070",
        "Operation": "Hoist Inspection must be completed at the beginning of each shift prior to use. Any abnormalities, defects, broken or missing parts are to be reported to your Supervisor immediately and a work order written. ",
        "MachineStatus": "Up/Down",
        "Exp. Time (min)": "",
        "When": "SOS",
        "OPL": "FM-CO-070"
    },
    {
        "Number": "4",
        "machineNumber": "Roll Dr.",
        "Component": "Machine Guarding",
        "CleaningTools": "Visual Inspection",
        "Operation": "Complete a visual check of machine guarding at the start of every shift and prior to re-start after maintenance. If guarding or safety System is missing or not functioning, all operation of the equipment shall stop until risk mitigation has occurred.",
        "MachineStatus": "Up/Down",
        "Exp. Time (min)": "",
        "When": "SOS",
        "OPL": ""
    },
    {
        "Number": "5",
        "machineNumber": "Roll Dr.",
        "Component": "Trash can",
        "CleaningTools": "Trash bag",
        "Operation": "Empty trash cans if 1/2 full",
        "MachineStatus": "Up",
        "Exp. Time (min)": "5",
        "When": "EOS",
        "OPL": "010-SW-AMP-003"
    },
    {
        "Number": "6",
        "machineNumber": "Roll Dr.",
        "Component": "Machine",
        "CleaningTools": "Air gun",
        "Operation": "Blow out machine",
        "MachineStatus": "Down",
        "Exp. Time (min)": "5",
        "When": "EOS",
        "OPL": "010-SL-069-007"
    },
    {
        "Number": "7",
        "machineNumber": "Roll Dr.",
        "Component": "Floor",
        "CleaningTools": "Broom",
        "Operation": "Sweep floor",
        "MachineStatus": "Up",
        "Exp. Time (min)": "10",
        "When": "EOS",
        "OPL": "010-SL-069-002"
    },
    {
        "Number": "8",
        "machineNumber": "Roll Dr.",
        "Component": "Fire extinguisher",
        "CleaningTools": "N/A",
        "Operation": "Visual inspection to make sure they are in place",
        "MachineStatus": "Up",
        "Exp. Time (min)": "2",
        "When": "EOS",
        "OPL": "010-SW-AMP-002"
    },
    {
        "Number": "9",
        "machineNumber": "Roll Dr.",
        "Component": "Supplies",
        "CleaningTools": "N/A",
        "Operation": "Return excess supplies to designated area",
        "MachineStatus": "Up",
        "Exp. Time (min)": "10",
        "When": "EOS",
        "OPL": "010-SL-069-003"
    },
    {
        "Number": "10",
        "machineNumber": "Roll Dr.",
        "Component": "Scrap",
        "CleaningTools": "N/A",
        "Operation": "Weigh scrap and empty into designated bin",
        "MachineStatus": "Up",
        "Exp. Time (min)": "5",
        "When": "EOS",
        "OPL": "010-CO-AMP-001"
    },
    {
        "Number": "11",
        "machineNumber": "Roll Dr.",
        "Component": "Tools",
        "CleaningTools": "N/A",
        "Operation": "All tools are clean, in good working condition and hung on tool boards",
        "MachineStatus": "Up",
        "Exp. Time (min)": "2",
        "When": "SOS/\nEOS",
        "OPL": "010-SL-069-004"
    },
    {
        "Number": "12",
        "machineNumber": "Roll Dr.",
        "Component": "Static bar",
        "CleaningTools": "Wire brush",
        "Operation": "Brush off bar",
        "MachineStatus": "Down",
        "Exp. Time (min)": "5",
        "When": "Any",
        "OPL": "010-SL-069-005"
    },
    {
        "Number": "14",
        "machineNumber": "Roll Dr.",
        "Component": "Ladders",
        "CleaningTools": "N/A",
        "Operation": "Visual inspection to ensure good condition",
        "MachineStatus": "Up",
        "Exp. Time (min)": "2",
        "When": "SOS",
        "OPL": ""
    },
    {
        "Number": "15",
        "machineNumber": "Roll Dr.",
        "Component": "SICK lens",
        "CleaningTools": "Approved rag",
        "Operation": "Wipe off lens on the SICK sensors using provided cloth",
        "MachineStatus": "Down",
        "Exp. Time (min)": "2",
        "When": "EOS",
        "OPL": "010-SL-116-006"
    },
    {
        "Number": "16",
        "machineNumber": "Roll Dr.",
        "Component": "6S",
        "CleaningTools": "N/A",
        "Operation": "6S locations are clearly marked and all items are in their designated locations",
        "MachineStatus": "Up/Down",
        "Exp. Time (min)": "2",
        "When": "SOS/EOS",
        "OPL": "010-SL-116-005          010-SL-116-004"
    },
    {
        "Number": "17",
        "machineNumber": "Roll Dr.",
        "Component": "Static String",
        "CleaningTools": "Visual Inspection",
        "Operation": "Verify that the static string is clean, replace if worn.",
        "MachineStatus": "Up/Down",
        "Exp. Time (min)": "1",
        "When": "SOS",
        "OPL": "010-CO-AMP-024"
    },
    {
        "Number": "1",
        "machineNumber": "Slt. 5",
        "Component": "Production Line",
        "CleaningTools": "Visual Inspection",
        "Operation": "Did you receive your production line in an adequate state of cleanliness and condition indicating the previous shift performed effective cleaning or inspection to prevent contamination?  If not, notify your crew leader and take corrective action.",
        "MachineStatus": "Up/Down",
        "Exp. Time (min)": "",
        "When": "SOS",
        "OPL": ""
    },
    {
        "Number": "2",
        "machineNumber": "Slt. 5",
        "Component": "Powered Industrial Hand Truck",
        "CleaningTools": "Visual Inspection of Items on FM SF 029",
        "Operation": "Powered Industrial Hand Truck Pre-Use Inspection must be completed prior to operating on each shift. If any items need attention NO NOT operate. Notify your crew leader and enter a work order for repair.",
        "MachineStatus": "Up/Down",
        "Exp. Time (min)": "",
        "When": "SOS",
        "OPL": "FM-SF-029"
    },
    {
        "Number": "3",
        "machineNumber": "Slt. 5",
        "Component": "Hoist",
        "CleaningTools": "Visual Inspection of Items on FM CO 070",
        "Operation": "Hoist Inspection must be completed at the beginning of each shift prior to use. Any abnormalities, defects, broken or missing parts are to be reported to your Supervisor immediately and a work order written. ",
        "MachineStatus": "Up/Down",
        "Exp. Time (min)": "",
        "When": "SOS",
        "OPL": "FM-CO-070"
    },
    {
        "Number": "4",
        "machineNumber": "Slt. 5",
        "Component": "Machine Guarding",
        "CleaningTools": "Visual Inspection",
        "Operation": "Complete a visual check of machine guarding at the start of every shift and prior to re-start after maintenance. If guarding or safety System is missing or not functioning, all operation of the equipment shall stop until risk mitigation has occurred.",
        "MachineStatus": "Up/Down",
        "Exp. Time (min)": "",
        "When": "SOS",
        "OPL": ""
    },
    {
        "Number": "5",
        "machineNumber": "Slt. 5",
        "Component": "Trash can",
        "CleaningTools": "Trash bag",
        "Operation": "Empty trash cans if 1/2 full",
        "MachineStatus": "Up",
        "Exp. Time (min)": "5",
        "When": "EOS",
        "OPL": "010-SW-AMP-003"
    },
    {
        "Number": "6",
        "machineNumber": "Slt. 5",
        "Component": "Machine",
        "CleaningTools": "Air gun",
        "Operation": "Blow out machine",
        "MachineStatus": "Down",
        "Exp. Time (min)": "5",
        "When": "EOS",
        "OPL": "010-SL-069-007"
    },
    {
        "Number": "7",
        "machineNumber": "Slt. 5",
        "Component": "Floor",
        "CleaningTools": "Broom",
        "Operation": "Sweep floor",
        "MachineStatus": "Up",
        "Exp. Time (min)": "10",
        "When": "EOS",
        "OPL": "010-SL-069-002"
    },
    {
        "Number": "8",
        "machineNumber": "Slt. 5",
        "Component": "Fire extinguisher",
        "CleaningTools": "N/A",
        "Operation": "Visual inspection to make sure they are in place",
        "MachineStatus": "Up",
        "Exp. Time (min)": "2",
        "When": "EOS",
        "OPL": "010-SW-AMP-002"
    },
    {
        "Number": "9",
        "machineNumber": "Slt. 5",
        "Component": "Supplies",
        "CleaningTools": "N/A",
        "Operation": "Return excess supplies to designated area",
        "MachineStatus": "Up",
        "Exp. Time (min)": "10",
        "When": "EOS",
        "OPL": "010-SL-069-003"
    },
    {
        "Number": "10",
        "machineNumber": "Slt. 5",
        "Component": "Scrap",
        "CleaningTools": "N/A",
        "Operation": "Weigh scrap and empty into designated bin",
        "MachineStatus": "Up",
        "Exp. Time (min)": "5",
        "When": "EOS",
        "OPL": "010-CO-AMP-001"
    },
    {
        "Number": "11",
        "machineNumber": "Slt. 5",
        "Component": "Tools",
        "CleaningTools": "N/A",
        "Operation": "All tools are clean, in good working condition and hung on tool boards",
        "MachineStatus": "Up",
        "Exp. Time (min)": "2",
        "When": "SOS/EOS",
        "OPL": "010-SL-069-004"
    },
    {
        "Number": "12",
        "machineNumber": "Slt. 5",
        "Component": "Static bar",
        "CleaningTools": "Wire brush",
        "Operation": "Brush off bar",
        "MachineStatus": "Down",
        "Exp. Time (min)": "5",
        "When": "Any",
        "OPL": "010-SL-069-005"
    },
    {
        "Number": "13",
        "machineNumber": "Slt. 5",
        "Component": "Slitting guard",
        "CleaningTools": "N/A",
        "Operation": "Visual inspection to make sure it is in place and functional",
        "MachineStatus": "Up",
        "Exp. Time (min)": "1",
        "When": "SOS",
        "OPL": "010-SL-116-001"
    },
    {
        "Number": "14",
        "machineNumber": "Slt. 5",
        "Component": "Slit blades",
        "CleaningTools": "N/A",
        "Operation": "Safely remove extra blades",
        "MachineStatus": "Down",
        "Exp. Time (min)": "2",
        "When": "SOS/EOS",
        "OPL": "010-SW-SP-001"
    },
    {
        "Number": "15",
        "machineNumber": "Slt. 5",
        "Component": "SICK lens",
        "CleaningTools": "Approved rag",
        "Operation": "Wipe off lens on the SICK sensors using provided cloth",
        "MachineStatus": "Down",
        "Exp. Time (min)": "2",
        "When": "EOS",
        "OPL": "010-SL-116-006"
    },
    {
        "Number": "16",
        "machineNumber": "Slt. 5",
        "Component": "6S",
        "CleaningTools": "N/A",
        "Operation": "6S locations are clearly marked and all items are in their designated locations",
        "MachineStatus": "Up/Down",
        "Exp. Time (min)": "2",
        "When": "SOS/EOS",
        "OPL": "010-SL-116-005    010-SL-116-004"
    },
    {
        "Number": "17",
        "machineNumber": "Slt. 5",
        "Component": "Corked Rollers",
        "CleaningTools": "N/A",
        "Operation": "Make sure cork is intact and check for wear on all corked rollers.",
        "MachineStatus": "Down",
        "Exp. Time (min)": "5",
        "When": "any",
        "OPL": "010-SL-069-012"
    },
    {
        "Number": "18",
        "machineNumber": "Slt. 5",
        "Component": "Lay on Rollers",
        "CleaningTools": "Rags/\ncleaner",
        "Operation": "Wipe down and ensure rollers are clean and turn freely.",
        "MachineStatus": "Down",
        "Exp. Time (min)": "10",
        "When": "",
        "OPL": "010-SL-069-020"
    },
    {
        "Number": "19",
        "machineNumber": "Slt. 5",
        "Component": "Static String",
        "CleaningTools": "Visual Inspection",
        "Operation": "Verify that the static string is clean, replace if worn.",
        "MachineStatus": "Up/Down",
        "Exp. Time (min)": "1",
        "When": "SOS",
        "OPL": "010-CO-AMP-024"
    },
    {
        "Number": "20",
        "machineNumber": "",
        "Component": "",
        "CleaningTools": "",
        "Operation": "",
        "MachineStatus": "",
        "Exp. Time (min)": "",
        "When": "",
        "OPL": ""
    },
    {
        "Number": "21",
        "machineNumber": "",
        "Component": "",
        "CleaningTools": "",
        "Operation": "",
        "MachineStatus": ""
    },
    {
        "Number": "1",
        "machineNumber": "Slt 6 & 7",
        "Component": "Production Line",
        "CleaningTools": "Visual Inspection",
        "Operation": "Did you receive your production line in an adequate state of cleanliness and condition indicating the previous shift performed effective cleaning or inspection to prevent contamination?  If not, notify your crew leader and take corrective action.",
        "MachineStatus": "Up/Down",
        "Exp. Time (min)": "",
        "When": "SOS",
        "OPL": ""
    },
    {
        "Number": "2",
        "machineNumber": "Slt 6 & 7",
        "Component": "Powered Industrial Hand Truck",
        "CleaningTools": "Visual Inspection of Items on FM SF 029",
        "Operation": "Powered Industrial Hand Truck Pre-Use Inspection must be completed prior to operating on each shift. If any items need attention NO NOT operate. Notify your crew leader and enter a work order for repair.",
        "MachineStatus": "Up/Down",
        "Exp. Time (min)": "",
        "When": "SOS",
        "OPL": "FM-SF-029"
    },
    {
        "Number": "3",
        "machineNumber": "Slt 6 & 7",
        "Component": "Hoist",
        "CleaningTools": "Visual Inspection of Items on FM CO 070",
        "Operation": "Hoist Inspection must be completed at the beginning of each shift prior to use. Any abnormalities, defects, broken or missing parts are to be reported to your Supervisor immediately and a work order written. ",
        "MachineStatus": "Up/Down",
        "Exp. Time (min)": "",
        "When": "SOS",
        "OPL": "FM-CO-070"
    },
    {
        "Number": "4",
        "machineNumber": "Slt 6 & 7",
        "Component": "Machine Guarding",
        "CleaningTools": "Visual Inspection",
        "Operation": "Complete a visual check of machine guarding at the start of every shift and prior to re-start after maintenance. If guarding or safety System is missing or not functioning, all operation of the equipment shall stop until risk mitigation has occurred.",
        "MachineStatus": "Up/Down",
        "Exp. Time (min)": "",
        "When": "SOS",
        "OPL": ""
    },
    {
        "Number": "5",
        "machineNumber": "Slt 6 & 7",
        "Component": "Trash can",
        "CleaningTools": "Trash bag",
        "Operation": "Empty trash cans if 1/2 full",
        "MachineStatus": "Up",
        "Exp. Time (min)": "5",
        "When": "EOS",
        "OPL": "010-SW-AMP-003"
    },
    {
        "Number": "6",
        "machineNumber": "Slt 6 & 7",
        "Component": "Machine",
        "CleaningTools": "Air gun",
        "Operation": "Blow out machine",
        "MachineStatus": "Down",
        "Exp. Time (min)": "5",
        "When": "EOS",
        "OPL": "010-SL-069-007"
    },
    {
        "Number": "7",
        "machineNumber": "Slt 6 & 7",
        "Component": "Floor",
        "CleaningTools": "Broom",
        "Operation": "Sweep floor",
        "MachineStatus": "Up",
        "Exp. Time (min)": "10",
        "When": "EOS",
        "OPL": "010-SL-069-002"
    },
    {
        "Number": "8",
        "machineNumber": "Slt 6 & 7",
        "Component": "Fire extinguisher",
        "CleaningTools": "N/A",
        "Operation": "Visual inspection to make sure they are in place",
        "MachineStatus": "Up",
        "Exp. Time (min)": "2",
        "When": "EOS",
        "OPL": "010-SW-AMP-002"
    },
    {
        "Number": "9",
        "machineNumber": "Slt 6 & 7",
        "Component": "Supplies",
        "CleaningTools": "N/A",
        "Operation": "Return excess supplies to designated area",
        "MachineStatus": "Up",
        "Exp. Time (min)": "10",
        "When": "EOS",
        "OPL": "010-SL-069-003"
    },
    {
        "Number": "10",
        "machineNumber": "Slt 6 & 7",
        "Component": "Scrap",
        "CleaningTools": "N/A",
        "Operation": "Weigh scrap and empty into designated bin",
        "MachineStatus": "Up",
        "Exp. Time (min)": "5",
        "When": "EOS",
        "OPL": "010-CO-AMP-001"
    },
    {
        "Number": "11",
        "machineNumber": "Slt 6 & 7",
        "Component": "Tools",
        "CleaningTools": "N/A",
        "Operation": "All tools are clean, in good working condition and hung on tool boards",
        "MachineStatus": "Up",
        "Exp. Time (min)": "2",
        "When": "SOS/\nEOS",
        "OPL": "010-SL-069-008"
    },
    {
        "Number": "12",
        "machineNumber": "Slt 6 & 7",
        "Component": "Static bar",
        "CleaningTools": "Wire brush",
        "Operation": "Brush off bar",
        "MachineStatus": "Down",
        "Exp. Time (min)": "5",
        "When": "Any",
        "OPL": "010-SL-069-005"
    },
    {
        "Number": "13",
        "machineNumber": "Slt 6 & 7",
        "Component": "Felt ",
        "CleaningTools": "Oil & rag",
        "Operation": "Oil rewind felt shafts",
        "MachineStatus": "Down",
        "Exp. Time (min)": "30",
        "When": "Shut down",
        "OPL": "010-4.09.07.32"
    },
    {
        "Number": "14",
        "machineNumber": "Slt 6 & 7",
        "Component": "SICK lens",
        "CleaningTools": "Approved rag",
        "Operation": "Wipe off lens on the SICK sensors using the provided cloth",
        "MachineStatus": "Down",
        "Exp. Time (min)": "2",
        "When": "EOS",
        "OPL": "010-SL-116-006"
    },
    {
        "Number": "15",
        "machineNumber": "Slt 6 & 7",
        "Component": "6S",
        "CleaningTools": "N/A",
        "Operation": "6S locations are clearly marked and all items are in their designated locations",
        "MachineStatus": "Up/Down",
        "Exp. Time (min)": "2",
        "When": "SOS/\nEOS",
        "OPL": "010-SL-116-005       010-SL-116-004"
    },
    {
        "Number": "16",
        "machineNumber": "Slt 6 & 7",
        "Component": "Corked Rollers",
        "CleaningTools": "N/A",
        "Operation": "Make sure cork is intact and check for wear on all corked rollers.",
        "MachineStatus": "Down",
        "Exp. Time (min)": "5",
        "When": "Any",
        "OPL": "010-SL-069-012"
    },
    {
        "Number": "17",
        "machineNumber": "Slt 6 & 7",
        "Component": "Lay on Rollers",
        "CleaningTools": "Rags/\nCleaner",
        "Operation": "Wipe down and ensure rollers are clean and turn freely.",
        "MachineStatus": "Down",
        "Exp. Time (min)": "10",
        "When": "",
        "OPL": "010-SL-069-020"
    },
    {
        "Number": "18",
        "machineNumber": "Slt 6 & 7",
        "Component": "Static String",
        "CleaningTools": "Visual Inspection",
        "Operation": "Verify that the statis string is clean, replace if worn.",
        "MachineStatus": "Up/Down",
        "Exp. Time (min)": "1",
        "When": "SOS",
        "OPL": "010-CO-AMP-024"
    },
    {
        "Number": "1",
        "machineNumber": "Slt. 8",
        "Component": "Production Line",
        "CleaningTools": "Visual Inspection",
        "Operation": "Did you receive your production line in an adequate state of cleanliness and condition indicating the previous shift performed effective cleaning or inspection to prevent contamination?  If not, notify your crew leader and take corrective action.",
        "MachineStatus": "Up/Down",
        "Exp. Time (min)": null,
        "When": "SOS",
        "OPL": " "
    },
    {
        "Number": "2",
        "machineNumber": "Slt. 8",
        "Component": "Powered Industrial Hand Truck",
        "CleaningTools": "Visual Inspection of Items on FM SF 029",
        "Operation": "Powered Industrial Hand Truck Pre-Use Inspection must be completed prior to operating on each shift. If any items need attention NO NOT operate. Notify your crew leader and enter a work order for repair.",
        "MachineStatus": "Up/Down",
        "Exp. Time (min)": null,
        "When": "SOS",
        "OPL": "FM-SF-029 "
    },
    {
        "Number": "3",
        "machineNumber": "Slt. 8",
        "Component": "Hoist",
        "CleaningTools": "Visual Inspection of Items on FM CO 070",
        "Operation": "Hoist Inspection must be completed at the beginning of each shift prior to use. Any abnormalities, defects, broken or missing parts are to be reported to your Supervisor immediately and a work order written. ",
        "MachineStatus": "Up/Down",
        "Exp. Time (min)": null,
        "When": "SOS",
        "OPL": "FM-CO-070 "
    },
    {
        "Number": "4",
        "machineNumber": "Slt. 8",
        "Component": "Machine Guarding",
        "CleaningTools": "Visual Inspection",
        "Operation": "Complete a visual check of machine guarding at the start of every shift and prior to re-start after maintenance. If guarding or safety System is missing or not functioning, all operation of the equipment shall stop until risk mitigation has occurred.",
        "MachineStatus": "Up/Down",
        "Exp. Time (min)": null,
        "When": "SOS",
        "OPL": " "
    },
    {
        "Number": "5",
        "machineNumber": "Slt. 8",
        "Component": "Trash can",
        "CleaningTools": "Trash bag",
        "Operation": "Empty trash cans if 1/2 full",
        "MachineStatus": "Up",
        "Exp. Time (min)": "5",
        "When": "EOS",
        "OPL": "010-SW-AMP-003 "
    },
    {
        "Number": "6",
        "machineNumber": "Slt. 8",
        "Component": "Machine",
        "CleaningTools": "Air gun",
        "Operation": "Blow out machine",
        "MachineStatus": "Down",
        "Exp. Time (min)": "5",
        "When": "EOS",
        "OPL": "010-SL-069-007 "
    },
    {
        "Number": "7",
        "machineNumber": "Slt. 8",
        "Component": "Floor",
        "CleaningTools": "Broom",
        "Operation": "Sweep floor",
        "MachineStatus": "Up",
        "Exp. Time (min)": "10",
        "When": "EOS",
        "OPL": "010-SL-069-002 "
    },
    {
        "Number": "8",
        "machineNumber": "Slt. 8",
        "Component": "Fire extinguisher",
        "CleaningTools": "N/A",
        "Operation": "Visual inspection to make sure they are in place",
        "MachineStatus": "Up",
        "Exp. Time (min)": "2",
        "When": "EOS",
        "OPL": "010-SW-AMP-002 "
    },
    {
        "Number": "9",
        "machineNumber": "Slt. 8",
        "Component": "Supplies",
        "CleaningTools": "N/A",
        "Operation": "Return excess supplies to designated area",
        "MachineStatus": "Up",
        "Exp. Time (min)": "10",
        "When": "EOS",
        "OPL": "010-SL-069-003 "
    },
    {
        "Number": "10",
        "machineNumber": "Slt. 8",
        "Component": "Scrap",
        "CleaningTools": "N/A",
        "Operation": "Weigh scrap and empty into designated bin",
        "MachineStatus": "Up",
        "Exp. Time (min)": "5",
        "When": "EOS",
        "OPL": "010-CO-AMP-001 "
    },
    {
        "Number": "11",
        "machineNumber": "Slt. 8",
        "Component": "Tools",
        "CleaningTools": "N/A",
        "Operation": "All tools are clean, in good working condition and hung on tool boards",
        "MachineStatus": "Up",
        "Exp. Time (min)": "2",
        "When": "SOS/EOS",
        "OPL": "010-SL-069-009 "
    },
    {
        "Number": "12",
        "machineNumber": "Slt. 8",
        "Component": "Static bar",
        "CleaningTools": "Wire brush",
        "Operation": "Brush off bar",
        "MachineStatus": "Down",
        "Exp. Time (min)": "5",
        "When": "Any",
        "OPL": "010-SL-069-005 "
    },
    {
        "Number": "13",
        "machineNumber": "Slt. 8",
        "Component": "Slitting guard",
        "CleaningTools": "N/A",
        "Operation": "Visual inspection to make sure it is in place and functional",
        "MachineStatus": "Up",
        "Exp. Time (min)": "1",
        "When": "SOS",
        "OPL": "010-SL-116-001 "
    },
    {
        "Number": "14",
        "machineNumber": "Slt. 8",
        "Component": "Slit blades",
        "CleaningTools": "N/A",
        "Operation": "Safely remove extra blades",
        "MachineStatus": "Down",
        "Exp. Time (min)": "2",
        "When": "SOS/EOS",
        "OPL": "010-SW-SP-001 "
    },
    {
        "Number": "15",
        "machineNumber": "Slt. 8",
        "Component": "Ladders",
        "CleaningTools": "N/A",
        "Operation": "Visual inspection to ensure good condition",
        "MachineStatus": "Up",
        "Exp. Time (min)": "2",
        "When": "SOS",
        "OPL": " "
    },
    {
        "Number": "16",
        "machineNumber": "Slt. 8",
        "Component": "SICK lens",
        "CleaningTools": "Approved rag",
        "Operation": "Wipe off lens on the SICK sensors using provided cloth",
        "MachineStatus": "Down",
        "Exp. Time (min)": "2",
        "When": "EOS",
        "OPL": "010-SL-116-006 "
    },
    {
        "Number": "17",
        "machineNumber": "Slt. 8",
        "Component": "6S",
        "CleaningTools": "N/A",
        "Operation": "6S locations are clearly marked and all items are in their designated locations",
        "MachineStatus": "Up/Down",
        "Exp. Time (min)": "2",
        "When": "SOS/EOS",
        "OPL": "010-SL-116-005          010-SL-116-004 "
    },
    {
        "Number": "18",
        "machineNumber": "Slt. 8",
        "Component": "Corked Rollers",
        "CleaningTools": "N/A",
        "Operation": "Make sure cork is intact and check for wear on all corked rollers",
        "MachineStatus": "Down",
        "Exp. Time (min)": "5",
        "When": "Any",
        "OPL": "010-SL-069-012 "
    },
    {
        "Number": "19",
        "machineNumber": "Slt. 8",
        "Component": "Static String",
        "CleaningTools": "Visual Inspection",
        "Operation": "Verify that the static string is clean, replace if worn.",
        "MachineStatus": "Up/Down",
        "Exp. Time (min)": "1",
        "When": "SOS",
        "OPL": "010-CO-AMP-024 "
    }, {
        "Number": "1",
        "machineNumber": "V-Fold",
        "Component": "Production Line",
        "CleaningTools": "Visual Inspection",
        "Operation": "Did you receive your production line in an adequate state of cleanliness and condition indicating the previous shift performed effective cleaning or inspection to prevent contamination?  If not, notify your crew leader and take corrective action.",
        "MachineStatus": "Up/Down",
        "Exp. Time (min)": null,
        "When": "SOS",
        "OPL": " "
    },
    {
        "Number": "2",
        "machineNumber": "V-Fold",
        "Component": "Powered Industrial Hand Truck",
        "CleaningTools": "Visual Inspection of Items on FM SF 029",
        "Operation": "Powered Industrial Hand Truck Pre-Use Inspection must be completed prior to operating on each shift. If any items need attention NO NOT operate. Notify your crew leader and enter a work order for repair.",
        "MachineStatus": "Up/Down",
        "Exp. Time (min)": null,
        "When": "SOS",
        "OPL": "FM-SF-029 "
    },
    {
        "Number": "3",
        "machineNumber": "V-Fold",
        "Component": "Hoist",
        "CleaningTools": "Visual Inspection of Items on FM CO 070",
        "Operation": "Hoist Inspection must be completed at the beginning of each shift prior to use. Any abnormalities, defects, broken or missing parts are to be reported to your Supervisor immediately and a work order written. ",
        "MachineStatus": "Up/Down",
        "Exp. Time (min)": null,
        "When": "SOS",
        "OPL": "FM-CO-070 "
    },
    {
        "Number": "4",
        "machineNumber": "V-Fold",
        "Component": "Machine Guarding",
        "CleaningTools": "Visual Inspection",
        "Operation": "Complete a visual check of machine guarding at the start of every shift and prior to re-start after maintenance. If guarding or safety System is missing or not functioning, all operation of the equipment shall stop until risk mitigation has occurred.",
        "MachineStatus": "Up/Down",
        "Exp. Time (min)": null,
        "When": "SOS",
        "OPL": " "
    },
    {
        "Number": "5",
        "machineNumber": "V-Fold",
        "Component": "Trash can",
        "CleaningTools": "Trash bag",
        "Operation": "Empty trash cans if 1/2 full",
        "MachineStatus": "Up",
        "Exp. Time (min)": "5",
        "When": "EOS",
        "OPL": "010-SW-AMP-003 "
    },
    {
        "Number": "6",
        "machineNumber": "V-Fold",
        "Component": "Machine",
        "CleaningTools": "Air gun",
        "Operation": "Blow out machine",
        "MachineStatus": "Down",
        "Exp. Time (min)": "5",
        "When": "EOS",
        "OPL": "010-SL-069-007 "
    },
    {
        "Number": "7",
        "machineNumber": "V-Fold",
        "Component": "Floor",
        "CleaningTools": "Broom",
        "Operation": "Sweep floor",
        "MachineStatus": "Up",
        "Exp. Time (min)": "10",
        "When": "EOS",
        "OPL": "010-SL-069-002 "
    },
    {
        "Number": "8",
        "machineNumber": "V-Fold",
        "Component": "Fire extinguisher",
        "CleaningTools": "N/A",
        "Operation": "Visual inspection to make sure they are in place",
        "MachineStatus": "Up",
        "Exp. Time (min)": "2",
        "When": "EOS",
        "OPL": "010-SW-AMP-002 "
    },
    {
        "Number": "9",
        "machineNumber": "V-Fold",
        "Component": "Supplies",
        "CleaningTools": "N/A",
        "Operation": "Return excess supplies to designated area",
        "MachineStatus": "Up",
        "Exp. Time (min)": "10",
        "When": "EOS",
        "OPL": "010-SL-069-003 "
    },
    {
        "Number": "10",
        "machineNumber": "V-Fold",
        "Component": "Scrap",
        "CleaningTools": "N/A",
        "Operation": "Weigh scrap and empty into designated bin",
        "MachineStatus": "Up",
        "Exp. Time (min)": "5",
        "When": "EOS",
        "OPL": "010-CO-AMP-001 "
    },
    {
        "Number": "11",
        "machineNumber": "V-Fold",
        "Component": "Tools",
        "CleaningTools": "N/A",
        "Operation": "All tools are clean, in good working condition and hung on tool boards",
        "MachineStatus": "Up",
        "Exp. Time (min)": "2",
        "When": "\"SOS/",
        "OPL": null
    },
    {
        "Number": "EOS\"",
        "machineNumber": "010-SL-069-004 ",
        "Component": null,
        "CleaningTools": null,
        "Operation": null,
        "MachineStatus": null,
        "Exp. Time (min)": null,
        "When": null,
        "OPL": null
    },
    {
        "Number": "12",
        "machineNumber": "V-Fold",
        "Component": "Static bar",
        "CleaningTools": "Wire brush",
        "Operation": "Brush off bar",
        "MachineStatus": "Down",
        "Exp. Time (min)": "5",
        "When": "Any",
        "OPL": "010-SL-069-005 "
    },
    {
        "Number": "13",
        "machineNumber": "V-Fold",
        "Component": "V-board",
        "CleaningTools": "Knife/cut gloves",
        "Operation": "Remove old Teflon and replace with new",
        "MachineStatus": "Down",
        "Exp. Time (min)": "10",
        "When": "Start up",
        "OPL": "010-SL-069-010 "
    },
    {
        "Number": "14",
        "machineNumber": "V-Fold",
        "Component": "Slit blades",
        "CleaningTools": "N/A",
        "Operation": "Safely remove extra blades",
        "MachineStatus": "Down",
        "Exp. Time (min)": "2",
        "When": "\"SOS/",
        "OPL": null
    },
    {
        "Number": "EOS\"",
        "machineNumber": "010-SW-SP-001 ",
        "Component": null,
        "CleaningTools": null,
        "Operation": null,
        "MachineStatus": null,
        "Exp. Time (min)": null,
        "When": null,
        "OPL": null
    },
    {
        "Number": "15",
        "machineNumber": "V-Fold",
        "Component": "Ladders",
        "CleaningTools": "N/A",
        "Operation": "Visual inspection to ensure good condition",
        "MachineStatus": "Up",
        "Exp. Time (min)": "2",
        "When": "SOS",
        "OPL": " "
    },
    {
        "Number": "16",
        "machineNumber": "V-Fold",
        "Component": "SICK lens",
        "CleaningTools": "Approved rag",
        "Operation": "Wipe off lens on the SICK sensors using provided cloth",
        "MachineStatus": "Down",
        "Exp. Time (min)": "2",
        "When": "EOS",
        "OPL": "010-SL-116-006 "
    },
    {
        "Number": "17",
        "machineNumber": "V-Fold",
        "Component": "6S",
        "CleaningTools": "N/A",
        "Operation": "6S locations are clearly marked and all items are in their designated locations",
        "MachineStatus": "Up/Down",
        "Exp. Time (min)": "2",
        "When": "SOS/EOS",
        "OPL": "010-SL-116-005          010-SL-116-004 "
    },
    {
        "Number": "18",
        "machineNumber": "V-Fold",
        "Component": "Static String",
        "CleaningTools": "Visual Inspection",
        "Operation": "Verify that the static string is clean, replace if worn.",
        "MachineStatus": "Up/Down",
        "Exp. Time (min)": "1",
        "When": "SOS",
        "OPL": "010-CO-AMP-024 "
    }
]
}